signing/__init__.py
signing/api_helper.py
signing/configuration.py
signing/decorators.py
signing/signing_client.py
signing/controllers/__init__.py
signing/controllers/base_controller.py
signing/controllers/misc_controller.py
signing/exceptions/__init__.py
signing/exceptions/api_exception.py
signing/http/__init__.py
signing/http/http_call_back.py
signing/http/http_client.py
signing/http/http_context.py
signing/http/http_method_enum.py
signing/http/http_request.py
signing/http/http_response.py
signing/http/requests_client.py
signing/models/__init__.py
tests/__init__.py
tests/http_response_catcher.py
tests/test_helper.py
tests/controllers/__init__.py
tests/controllers/controller_test_base.py
tests/controllers/test_misc_controller.py
signing-3.dist-info/LICENSE
signing-3.dist-info/METADATA
signing-3.dist-info/WHEEL
signing-3.dist-info/top_level.txt
signing-3.dist-info/RECORD
